collective.excelexport-2.0-py3.12-nspkg.pth
collective/excelexport/__init__.py
collective/excelexport/configure.zcml
collective/excelexport/interfaces.py
collective/excelexport/minimal.zcml
collective/excelexport/restapi.py
collective/excelexport/restapi.zcml
collective/excelexport/setuphandlers.py
collective/excelexport/styles.py
collective/excelexport/testing.py
collective/excelexport/testing.zcml
collective/excelexport/upgrades.py
collective/excelexport/upgrades.zcml
collective/excelexport/view.py
collective/excelexport/datasources/__init__.py
collective/excelexport/datasources/base.py
collective/excelexport/datasources/configure.zcml
collective/excelexport/datasources/folder.py
collective/excelexport/datasources/search.py
collective/excelexport/datasources/eeafaceted/__init__.py
collective/excelexport/datasources/eeafaceted/configure.zcml
collective/excelexport/datasources/eeafaceted/datasource.py
collective/excelexport/datasources/eeafaceted/view.py
collective/excelexport/exportables/__init__.py
collective/excelexport/exportables/base.py
collective/excelexport/exportables/configure.zcml
collective/excelexport/exportables/dexterityfields.py
collective/excelexport/exportables/dexterityfields.zcml
collective/excelexport/locales/collective.excelexport.pot
collective/excelexport/locales/plone.pot
collective/excelexport/locales/update.sh
collective/excelexport/locales/es/LC_MESSAGES/collective.excelexport.po
collective/excelexport/locales/es/LC_MESSAGES/plone.po
collective/excelexport/locales/fr/LC_MESSAGES/collective.excelexport.po
collective/excelexport/locales/fr/LC_MESSAGES/plone.po
collective/excelexport/profiles/default/browserlayer.xml
collective/excelexport/profiles/default/metadata.xml
collective/excelexport/profiles/default/registry.xml
collective/excelexport/profiles/testing/metadata.xml
collective/excelexport/profiles/testing/types.xml
collective/excelexport/profiles/testing/types/member.xml
collective/excelexport/profiles/testing/types/member2.xml
collective_excelexport-2.0.dist-info/METADATA
collective_excelexport-2.0.dist-info/WHEEL
collective_excelexport-2.0.dist-info/entry_points.txt
collective_excelexport-2.0.dist-info/namespace_packages.txt
collective_excelexport-2.0.dist-info/top_level.txt
collective_excelexport-2.0.dist-info/RECORD
