Metadata-Version: 2.4
Name: collective.excelexport
Version: 2.0
Summary: Export dexterity contents in an excel file, one column by field
Home-page: http://pypi.python.org/pypi/collective.excelexport
Author: Thomas Desvenain
Author-email: thomas.desvenain@gmail.com
License: GPL
Keywords: Export,Plone,Excel
Classifier: Environment :: Web Environment
Classifier: Framework :: Plone
Classifier: Framework :: Plone :: 6.0
Classifier: Framework :: Plone :: 6.1
Classifier: Framework :: Plone :: Addon
Classifier: Programming Language :: Python
Classifier: Programming Language :: Python :: 3.9
Classifier: Programming Language :: Python :: 3.10
Classifier: Programming Language :: Python :: 3.11
Classifier: Programming Language :: Python :: 3.12
Classifier: Programming Language :: Python :: 3.13
Requires-Dist: Plone
Requires-Dist: plone.api
Requires-Dist: setuptools
Requires-Dist: xlwt
Provides-Extra: test
Requires-Dist: collective.z3cform.datagridfield; extra == "test"
Requires-Dist: ecreall.helpers.testing; extra == "test"
Requires-Dist: plone.app.testing; extra == "test"
Requires-Dist: plone.app.dexterity; extra == "test"
Requires-Dist: plone.app.relationfield; extra == "test"
Requires-Dist: xlrd; extra == "test"
Dynamic: author
Dynamic: author-email
Dynamic: classifier
Dynamic: description
Dynamic: home-page
Dynamic: keywords
Dynamic: license
Dynamic: provides-extra
Dynamic: requires-dist
Dynamic: summary
